Metadata-Version: 1.0
Name: ud4d
Version: 0.1.4
Summary: USB Device Detector for Docker usage. Support Linux only.
Home-page: https://github.com/doringland/ud4d
Author: williamfzc
Author-email: fengzc@vip.qq.com
License: UNKNOWN
Platform: UNKNOWN
